<?xml version="1.0" encoding="UTF-8"?>

<Schedule xmlns="http://hl7.org/fhir">
  <id value="Example-Schedule-d83f2b28"/>
  <text>
    <status value="generated"/><div xmlns="http://www.w3.org/1999/xhtml"><h1>SEGMENTO NARRATIVO</h1></div>
  </text>
  <extension id="quotaPatient" url="https://www.digitalware.com.co/salud/fhir/StructureDefinition/quota-patients">
    <valueInteger value="1"/>
  </extension>
  <extension id="availableTelemedicine" url="https://www.digitalware.com.co/salud/fhir/StructureDefinition/available-telemedicine">
    <valueBoolean value="false"/>
  </extension>
  <extension id="slotTime" url="https://www.digitalware.com.co/salud/fhir/StructureDefinition/slots-time">
    <valueInteger value="30"/>
  </extension>
  <identifier>
    <system value="https://www.digitalware.com.co/salud/fhir/identifiers/agenda-identifiers"/>
    <value value="403"/>
  </identifier>
  <active value="true"/>
  <serviceCategory>
    <text value="Pediatrica"/>
  </serviceCategory>
  <serviceType>
    <coding>
      <system value="http://snomed.info/sct"/>
      <code value="185316007"/>
      <display value="encuentro indirecto"/>
    </coding>
  </serviceType>
  <serviceType>
    <coding>
      <system value="http://snomed.info/sct"/>
      <code value="308467007"/>
      <display value="atendido en establecimiento"/>
    </coding>
  </serviceType>
  <specialty>
    <coding>
      <system value="http://snomed.info/sct"/>
      <code value="394586005"/>
      <display value="Ginecologia"/>
    </coding>
  </specialty>
  <actor>
    <reference value="Location/Example-LocationBuilding-7412389635sdf556d"/>
  </actor>
  <actor>
    <reference value="Location/Example-LocationRoom-1245687952"/>
  </actor>
  <actor>
    <reference value="Location/Example-LocationArea-789789789789"/>
  </actor>
  <planningHorizon>
    <extension id="hoursOfOperation" url="https://www.digitalware.com.co/salud/fhir/StrutureDefinition/hours-of-operation">
      <extension id="day" url="day">
        <valueCode value="mon"/>
      </extension>
      <extension id="startTime" url="startTime">
        <valueTime value="08:00:00"/>
      </extension>
      <extension id="endTime" url="endTime">
        <valueTime value="12:00:00"/>
      </extension>
    </extension>
    <extension id="hoursOfOperation" url="https://www.digitalware.com.co/salud/fhir/StrutureDefinition/hours-of-operation">
      <extension id="day" url="day">
        <valueCode value="tue"/>
      </extension>
      <extension id="startTime" url="startTime">
        <valueTime value="14:00:00"/>
      </extension>
      <extension id="endTime" url="endTime">
        <valueTime value="16:00:00"/>
      </extension>
    </extension>
    <start value="2021-01-01"/>
    <end value="2021-01-31"/>
  </planningHorizon>
  <comment value="FONASA, ISAPRE, CAPREDENA, DIPRECA, SISA"/>
</Schedule>